distutils_build_without_typehints/__init__.py
distutils_build_without_typehints/build_without_typehints.py
distutils_build_without_typehints/strip_type_hints.py
distutils_build_without_typehints-0.6.1.dist-info/DESCRIPTION.rst
distutils_build_without_typehints-0.6.1.dist-info/METADATA
distutils_build_without_typehints-0.6.1.dist-info/RECORD
distutils_build_without_typehints-0.6.1.dist-info/WHEEL
distutils_build_without_typehints-0.6.1.dist-info/entry_points.txt
distutils_build_without_typehints-0.6.1.dist-info/metadata.json
distutils_build_without_typehints-0.6.1.dist-info/top_level.txt
distutils_build_without_typehints-0.6.1.dist-info/zip-safe
