Metadata-Version: 2.0
Name: distutils-build-without-typehints
Version: 0.6.1
Summary: A build command that strips typehints from the code during the build.
Home-page: https://github.com/wheerd/distutils-build-without-typehints
Author: Manuel Krebber
Author-email: admin@wheerd.de
License: MIT
Platform: UNKNOWN
Classifier: Development Status :: 3 - Alpha
Classifier: Intended Audience :: Developers
Classifier: License :: OSI Approved :: MIT License
Classifier: Programming Language :: Python
Classifier: Programming Language :: Python :: 2
Classifier: Programming Language :: Python :: 2.7
Classifier: Programming Language :: Python :: 3
Classifier: Programming Language :: Python :: 3.3
Classifier: Programming Language :: Python :: 3.4
Classifier: Programming Language :: Python :: 3.5
Classifier: Programming Language :: Python :: 3.6
